beakerx_clojure/__init__.py
beakerx_clojure/_version.py
beakerx_clojure/commands.py
beakerx_clojure/install.py
beakerx_clojure/kernel/kernel.json
beakerx_clojure/kernel/logo-32x32.png
beakerx_clojure/kernel/logo-64x64.png
beakerx_clojure/kernel/ext/beakerx-runtimetools-1.6-SNAPSHOT.jar
beakerx_clojure/kernel/ext/beakerx-runtimetools-2.0-SNAPSHOT.jar
beakerx_clojure/kernel/lib/aether-api-1.13.1.jar
beakerx_clojure/kernel/lib/aether-connector-file-1.13.1.jar
beakerx_clojure/kernel/lib/aether-connector-wagon-1.13.1.jar
beakerx_clojure/kernel/lib/aether-impl-1.13.1.jar
beakerx_clojure/kernel/lib/aether-spi-1.13.1.jar
beakerx_clojure/kernel/lib/aether-util-1.13.1.jar
beakerx_clojure/kernel/lib/annotations-13.0.jar
beakerx_clojure/kernel/lib/asm-3.3.1.jar
beakerx_clojure/kernel/lib/assertj-core-3.6.1.jar
beakerx_clojure/kernel/lib/beakerx-kernel-base-1.6-SNAPSHOT.jar
beakerx_clojure/kernel/lib/beakerx-kernel-base-2.0-SNAPSHOT.jar
beakerx_clojure/kernel/lib/beakerx-kernel-base-api-1.6-SNAPSHOT.jar
beakerx_clojure/kernel/lib/beakerx-kernel-base-api-2.0-SNAPSHOT.jar
beakerx_clojure/kernel/lib/cglib-2.2.2.jar
beakerx_clojure/kernel/lib/clojure-1.9.0.jar
beakerx_clojure/kernel/lib/clojure.jar
beakerx_clojure/kernel/lib/commons-beanutils-1.9.3.jar
beakerx_clojure/kernel/lib/commons-cli-1.2.jar
beakerx_clojure/kernel/lib/commons-codec-1.10.jar
beakerx_clojure/kernel/lib/commons-collections-3.2.2.jar
beakerx_clojure/kernel/lib/commons-io-2.5.jar
beakerx_clojure/kernel/lib/commons-lang3-3.6.jar
beakerx_clojure/kernel/lib/commons-logging-1.2.jar
beakerx_clojure/kernel/lib/commons-text-1.1.jar
beakerx_clojure/kernel/lib/core.specs.alpha-0.1.24.jar
beakerx_clojure/kernel/lib/dynapath-0.2.3.jar
beakerx_clojure/kernel/lib/fluent-hc-4.5.5.jar
beakerx_clojure/kernel/lib/gson-2.3.1.jar
beakerx_clojure/kernel/lib/hamcrest-core-1.3.jar
beakerx_clojure/kernel/lib/httpclient-4.5.5.jar
beakerx_clojure/kernel/lib/httpcore-4.4.9.jar
beakerx_clojure/kernel/lib/ivy-2.4.0.jar
beakerx_kernel_clojure-2.0.0.dist-info/METADATA
beakerx_kernel_clojure-2.0.0.dist-info/WHEEL
beakerx_kernel_clojure-2.0.0.dist-info/entry_points.txt
beakerx_kernel_clojure-2.0.0.dist-info/top_level.txt
beakerx_kernel_clojure-2.0.0.dist-info/RECORD
